isat_sibyl-1.0.12.data/scripts/sibyl.py
isat_sibyl-1.0.12.dist-info/licenses/LICENSE
sibyl/Pipfile
sibyl/__init__.py
sibyl/build.py
sibyl/dev.py
sibyl/hot-reload.html
sibyl/init.py
sibyl/requirements.txt
sibyl/settings.yaml
sibyl/sibyl.py
sibyl/components/Accordion.html
sibyl/components/Address.html
sibyl/components/Button.html
sibyl/components/ButtonAnchor.html
sibyl/components/ButtonHref.html
sibyl/components/ButtonPage.html
sibyl/components/ButtonType.html
sibyl/components/Card.html
sibyl/components/Carousel.html
sibyl/components/CarouselSlide.html
sibyl/components/Chip.html
sibyl/components/Dialog.html
sibyl/components/DoubleImageService.html
sibyl/components/Drawer.html
sibyl/components/DrawerItem.html
sibyl/components/DrawerItemInner.html
sibyl/components/Footer.html
sibyl/components/Header.html
sibyl/components/Icon.html
sibyl/components/ImageService.html
sibyl/components/Markdown.html
sibyl/components/MaterialIcon.html
sibyl/components/SkewedBanner.html
sibyl/components/SkewedTitle.html
sibyl/components/Social.html
sibyl/components/Spinner.html
sibyl/helpers/__init__.py
sibyl/helpers/component.py
sibyl/helpers/requirement.py
sibyl/helpers/settings.py
sibyl/helpers/shutil_compat.py
sibyl/helpers/version.py
sibyl/layouts/main_layout.html
sibyl/locales/en.json
sibyl/locales/global.json
sibyl/locales/pt.json
sibyl/pages/index.html
sibyl/pages/start.html
sibyl/sibyl-static/flex.css
sibyl/sibyl-static/microsite.js
sibyl/sibyl-static/spa.js
sibyl/static/logo.svg
sibyl/static/robots.txt
sibyl/static/sibyl.svg
sibyl/static/styles.css
sibyl/static/variables.css
sibyl/static/favicon/android-chrome-192x192.png
sibyl/static/favicon/android-chrome-512x512.png
sibyl/static/favicon/apple-touch-icon.png
sibyl/static/favicon/browserconfig.xml
sibyl/static/favicon/favicon-16x16.png
sibyl/static/favicon/favicon-32x32.png
sibyl/static/favicon/favicon.ico
sibyl/static/favicon/mstile-144x144.png
sibyl/static/favicon/mstile-150x150.png
sibyl/static/favicon/mstile-310x150.png
sibyl/static/favicon/mstile-310x310.png
isat_sibyl-1.0.12.dist-info/METADATA
isat_sibyl-1.0.12.dist-info/WHEEL
isat_sibyl-1.0.12.dist-info/top_level.txt
isat_sibyl-1.0.12.dist-info/RECORD
