Metadata-Version: 2.4
Name: isat-sibyl
Version: 1.0.12
Summary: Sibyl static site generator
Home-page: https://github.com/isat-sibyl/sibyl
Author: Pedro Cavalheiro
Author-email: pedro.cavalheiro@isat.pt
License: All rights reserved
Project-URL: Bug Tracker, https://github.com/isat-sibyl/sibyl/issues
License-File: LICENSE
Requires-Dist: beautifulsoup4>=4.12.2
Requires-Dist: PyYAML>=6.0
Requires-Dist: soupsieve>=2.4
Requires-Dist: typing_extensions>=4.5.0
Requires-Dist: Markdown>=3.4.3
Requires-Dist: Pygments>=2.15.1
Provides-Extra: dev
Requires-Dist: watchdog>=3.0.0; extra == "dev"
Requires-Dist: websockets>=11.0.1; extra == "dev"
Requires-Dist: pre-commit>=3.2.2; extra == "dev"
Dynamic: author
Dynamic: author-email
Dynamic: description
Dynamic: description-content-type
Dynamic: home-page
Dynamic: license
Dynamic: license-file
Dynamic: project-url
Dynamic: provides-extra
Dynamic: requires-dist
Dynamic: summary
